snark/__init__.py
snark/config.py
snark/exceptions.py
snark/log.py
snark/main.py
snark/token_manager.py
snark/cli/__init__.py
snark/cli/auth.py
snark/cli/connect.py
snark/cli/data_transfer.py
snark/cli/hyper.py
snark/cli/pod_control.py
snark/cli/store.py
snark/cli/utils.py
snark/client/__init__.py
snark/client/auth.py
snark/client/base.py
snark/client/hyper_control.py
snark/client/pod_control.py
snark/client/store_control.py
snark/development/__init__.py
snark/development/dev.py
snark/development/local.py
snark/infer/__init__.py
snark/infer/api.py
snark/infer/message_processor.py
snark-0.5.2.2.dist-info/LICENSE
snark-0.5.2.2.dist-info/METADATA
snark-0.5.2.2.dist-info/WHEEL
snark-0.5.2.2.dist-info/entry_points.txt
snark-0.5.2.2.dist-info/top_level.txt
snark-0.5.2.2.dist-info/RECORD
