Metadata-Version: 2.1
Name: snark
Version: 0.5.2.2
Summary: Snark AI command line client
Home-page: https://github.com/snarkai/snark-cli
Author: Snark AI Inc.
Author-email: support@snarkai.com
License: UNKNOWN
Keywords: snark
Platform: UNKNOWN
Requires-Python: >=3
Requires-Dist: awscli
Requires-Dist: click (<7,>=6.7)
Requires-Dist: clint (<1,>=0.5.1)
Requires-Dist: marshmallow (<3.0.0b0,>=2.11.1)
Requires-Dist: outdated (>=0.2.0)
Requires-Dist: pytz (>=2016.10)
Requires-Dist: pyyaml
Requires-Dist: requests-toolbelt (<1,>=0.7.1)
Requires-Dist: requests (<3,>=2.12.4)
Requires-Dist: tabulate (<1,>=0.7.7)
